py_eio_logic/__init__.py
py_eval_in_order-0.1.3.dist-info/licenses/LICENSE.txt
py_eval_in_order-0.1.3.dist-info/METADATA
py_eval_in_order-0.1.3.dist-info/WHEEL
py_eval_in_order-0.1.3.dist-info/top_level.txt
py_eval_in_order-0.1.3.dist-info/RECORD
