Metadata-Version: 2.4
Name: py-eval_in_order
Version: 0.1.3
Summary: A Python package for evaluating multiple boolean conditions (uses eval) IN ORDER.
Home-page: https://github.com/MostafaHanii/py_eio
Author: Mostafa Hani
Author-email: mostafahanii213@gmail.com
Keywords: boolean eval conditions logic
Classifier: Programming Language :: Python :: 3
Classifier: License :: OSI Approved :: MIT License
Classifier: Operating System :: OS Independent
Classifier: Development Status :: 3 - Alpha
Classifier: Intended Audience :: Developers
Classifier: Topic :: Software Development :: Libraries :: Python Modules
Requires-Python: >=3.6
License-File: LICENSE.txt
Dynamic: author
Dynamic: author-email
Dynamic: classifier
Dynamic: description
Dynamic: description-content-type
Dynamic: home-page
Dynamic: keywords
Dynamic: license-file
Dynamic: requires-python
Dynamic: summary
